s3edit/__init__.py
s3edit/__main__.py
s3edit/cli.py
s3edit/core.py
s3edit-0.0.1.dist-info/LICENSE
s3edit-0.0.1.dist-info/METADATA
s3edit-0.0.1.dist-info/WHEEL
s3edit-0.0.1.dist-info/entry_points.txt
s3edit-0.0.1.dist-info/top_level.txt
s3edit-0.0.1.dist-info/RECORD
