Metadata-Version: 2.1
Name: s3edit
Version: 0.0.1
Summary: Edit files from S3 directly with your default editor.
Home-page: https://github.com/bgyori/s3edit
Author: Benjamin M. Gyori
Author-email: ben.gyori@gmail.com
License: UNKNOWN
Platform: UNKNOWN
Classifier: Development Status :: 4 - Beta
Classifier: Environment :: Console
Classifier: Intended Audience :: Developers
Classifier: License :: OSI Approved :: BSD License
Classifier: Operating System :: OS Independent
Classifier: Programming Language :: Python :: 3 :: Only
Requires-Dist: boto3
Requires-Dist: click
